{"status":"20000","statusDesc":"Success","products":[{"materialCode":"NEW0APXM256-GD01","prices":[{"priceType":"EUP","priceIncludeVat":30900,"priceExcludeVat":28878.5,"vatRate":"7.00","vatAmount":2021.5,"effectiveDate":"2020-05-07T17:00:00Z"}],"trades":[{"tradeNo":"TP21060221","payAdvances":[],"discounts":[],"payments":[{"cardType":"MASTER","method":"CC","banks":[{"bankAbbr":"ACS","installments":[{"installId":20,"installmentAbb":"0%  3 เดือน ( 3 M)"},{"installId":22,"installmentAbb":"0%  6 เดือน ( 6 M)"},{"installId":27,"installmentAbb":"0% 10 เดือน (10 M)"}],"bankDescEn":"Ayudlhya Card Services","bankDescTh":"อยุธยาคาร์ด เซอร์วิสเซส","imageUrl":"https://cpc.ais.co.th/CPC-FE-WEB/api/contents/upload/ACS_BAY03.png"},{"bankAbbr":"AEON","installments":[{"installId":294,"installmentAbb":"0% 10 เดือน (10 M)"},{"installId":51837,"installmentAbb":"0% 18 เดือน (18 M)"},{"installId":51941,"installmentAbb":"0.59% 20 เดือน (20M)"},{"installId":51961,"installmentAbb":"0.59% 12 เดือน (12M)"},{"installId":52001,"installmentAbb":"0.69% 24 เดือน (24 M)"}],"bankDescEn":"AEON THANA SINSAP (THAILAND) PCL.","bankDescTh":"บริษัทอิออนธนสินทรัพย์ (ไทยแลนด์) จำกัด (มหาชน)","imageUrl":"https://cpc.ais.co.th/CPC-FE-WEB/api/contents/upload/AEON_AEON-logo.png"},{"bankAbbr":"BAY","installments":[{"installId":38,"installmentAbb":"0%  3 เดือน ( 3 M)"},{"installId":41,"installmentAbb":"0%  6 เดือน ( 6 M)"},{"installId":47,"installmentAbb":"0% 10 เดือน (10 M)"}],"bankDescEn":"BANK OF AYUDHAYA PUBLIC COMPANY LIMITED","bankDescTh":"กรุงศรีอยุธยา จำกัด (มหาชน)","imageUrl":"https://cpc.ais.co.th/CPC-FE-WEB/api/contents/upload/BAY_BAY.png"},{"bankAbbr":"BBL","installments":[{"installId":60,"installmentAbb":"0% 4 เดือน (4 M)"},{"installId":65,"installmentAbb":"0%  6 เดือน ( 6 M)"},{"installId":71,"installmentAbb":"0% 10 เดือน (10 M)"}],"bankDescEn":"BANGKOK BANK PUBLIC COMPANY LIMITED","bankDescTh":"กรุงเทพ จำกัด (มหาชน)","imageUrl":"https://cpc.ais.co.th/CPC-FE-WEB/api/contents/upload/BBL_BBL.png"},{"bankAbbr":"CITI","installments":[{"installId":309,"installmentAbb":"0% 4 เดือน (4 M)"},{"installId":314,"installmentAbb":"0%  6 เดือน ( 6 M)"},{"installId":320,"installmentAbb":"0% 10 เดือน (10 M)"}],"bankDescEn":"CITIBANK N.A.","bankDescTh":"ซิตี้แบงก์","imageUrl":"https://cpc.ais.co.th/CPC-FE-WEB/api/contents/upload/CITI_CITI.png"},{"bankAbbr":"CITIREADY","installments":[{"installId":432,"installmentAbb":"0% 4 เดือน (4 M)"},{"installId":436,"installmentAbb":"0%  6 เดือน ( 6 M)"},{"installId":440,"installmentAbb":"0% 10 เดือน (10 M)"},{"installId":445,"installmentAbb":"0% 24 เดือน (24 M)"},{"installId":524,"installmentAbb":"0% 18 เดือน (18 M)"},{"installId":884,"installmentAbb":"0% 12 เดือน (12 M)"},{"installId":51883,"installmentAbb":"0% 30 เดือน (30M)"},{"installId":51886,"installmentAbb":"0%  40 เดือน (40 M)"}],"bankDescEn":"CITIBANK Ready","bankDescTh":"ซิตี้แบงก์ เรดดี้เครดิต","imageUrl":"https://cpc.ais.co.th/CPC-FE-WEB/api/contents/upload/CITIREADY_citibank02.jpg"},{"bankAbbr":"CT","installments":[{"installId":2,"installmentAbb":"0%  3 เดือน ( 3 M)"},{"installId":2,"installmentAbb":"0%  3 เดือน ( 3 M)"},{"installId":4,"installmentAbb":"0%  6 เดือน ( 6 M)"},{"installId":4,"installmentAbb":"0%  6 เดือน ( 6 M)"},{"installId":10,"installmentAbb":"0% 10 เดือน (10 M)"},{"installId":10,"installmentAbb":"0% 10 เดือน (10 M)"}],"bankDescEn":"Central","bankDescTh":"เซ็นทรัล","imageUrl":"https://cpc.ais.co.th/CPC-FE-WEB/api/contents/upload/CT_ct_logo.png"},{"bankAbbr":"FCC","installments":[{"installId":108,"installmentAbb":"0%  6 เดือน ( 6 M)"},{"installId":112,"installmentAbb":"0% 10 เดือน (10 M)"},{"installId":136,"installmentAbb":"0.89% 20 เดือน (20 M)"},{"installId":461,"installmentAbb":"0% 15 เดือน (15 M)"},{"installId":722,"installmentAbb":"0% 20 เดือน (20 M)"},{"installId":846,"installmentAbb":"0% 12 เดือน (12 M)"}],"bankDescEn":"Frist Choice Credit Card","bankDescTh":"บัตรเครดิต เฟิร์สช้อยส์","imageUrl":"https://cpc.ais.co.th/CPC-FE-WEB/api/contents/upload/FCC_fcc_logo.png"},{"bankAbbr":"KBNK","installments":[{"installId":350,"installmentAbb":"0% 4 เดือน (4 M)"},{"installId":355,"installmentAbb":"0%  6 เดือน ( 6 M)"},{"installId":361,"installmentAbb":"0% 10 เดือน (10 M)"},{"installId":874,"installmentAbb":"0% 12 เดือน (12 M)"},{"installId":876,"installmentAbb":"0% 18 เดือน (18 M)"},{"installId":878,"installmentAbb":"0% 24 เดือน (24 M)"},{"installId":51860,"installmentAbb":"0%  36 เดือน (36 M)"}],"bankDescEn":"KASIKORNBANK PUBLIC COMPANY LIMITED","bankDescTh":"กสิกรไทย จำกัด (มหาชน)","imageUrl":"https://cpc.ais.co.th/CPC-FE-WEB/api/contents/upload/KBNK_kBank.png"},{"bankAbbr":"KTB","installments":[{"installId":161,"installmentAbb":"0%  6 เดือน ( 6 M)"},{"installId":167,"installmentAbb":"0% 10 เดือน (10 M)"},{"installId":462,"installmentAbb":"0% 12 เดือน (12 M)"},{"installId":849,"installmentAbb":"0% 18 เดือน (18 M)"},{"installId":51765,"installmentAbb":"0.59% 20 เดือน (20M)"}],"bankDescEn":"KRUNG THAI BANK PUBLIC COMPANY LIMITED","bankDescTh":"กรุงไทย จำกัด (มหาชน)","imageUrl":"https://cpc.ais.co.th/CPC-FE-WEB/api/contents/upload/KTB_KTB.png"},{"bankAbbr":"NBNK","installments":[{"installId":373,"installmentAbb":"0% 4 เดือน (4 M)"},{"installId":378,"installmentAbb":"0%  6 เดือน ( 6 M)"},{"installId":384,"installmentAbb":"0% 10 เดือน (10 M)"},{"installId":395,"installmentAbb":"0% 20 เดือน (20 M)"},{"installId":397,"installmentAbb":"0% 24 เดือน (24 M)"}],"bankDescEn":"THANACHART BANK PUBLIC COMPANY LIMITED","bankDescTh":"ธนชาต จำกัด(มหาชน)","imageUrl":"https://cpc.ais.co.th/CPC-FE-WEB/api/contents/upload/NBNK_65-NBNK-Logo.png"},{"bankAbbr":"SCB","installments":[{"installId":191,"installmentAbb":"0% 4 เดือน (4 M)"},{"installId":196,"installmentAbb":"0%  6 เดือน ( 6 M)"},{"installId":202,"installmentAbb":"0% 10 เดือน (10 M)"},{"installId":214,"installmentAbb":"0% 24 เดือน (24 M)"},{"installId":463,"installmentAbb":"0% 18 เดือน (18 M)"},{"installId":854,"installmentAbb":"0% 12 เดือน (12 M)"}],"bankDescEn":"SIAM COMMERCIAL BANK PUBLIC COMPANY LIMITED","bankDescTh":"ไทยพาณิชย์ จำกัด (มหาชน)","imageUrl":"https://cpc.ais.co.th/CPC-FE-WEB/api/contents/upload/SCB_SCB.png"},{"bankAbbr":"TCS","installments":[{"installId":239,"installmentAbb":"0%  3 เดือน ( 3 M)"},{"installId":239,"installmentAbb":"0%  3 เดือน ( 3 M)"},{"installId":241,"installmentAbb":"0%  6 เดือน ( 6 M)"},{"installId":241,"installmentAbb":"0%  6 เดือน ( 6 M)"},{"installId":246,"installmentAbb":"0% 10 เดือน (10 M)"},{"installId":246,"installmentAbb":"0% 10 เดือน (10 M)"}],"bankDescEn":"TESCO LOTUS VISA CARD","bankDescTh":"บัตรเครดิต เทสโก้ โลตัส วีซ่า","imageUrl":"https://cpc.ais.co.th/CPC-FE-WEB/api/contents/upload/TCS_TescoLotus-CreditCard.png"},{"bankAbbr":"TMB","installments":[{"installId":981,"installmentAbb":"0% 4 เดือน (4 M)"},{"installId":982,"installmentAbb":"0% 10 เดือน (10 M)"},{"installId":51814,"installmentAbb":"0%  6 เดือน ( 6 M)"},{"installId":51818,"installmentAbb":"0% 20 เดือน (20 M)"},{"installId":51819,"installmentAbb":"0% 24 เดือน (24 M)"}],"bankDescEn":"THAI MILITARY BANK PUBLIC COMPANY LIMITED","bankDescTh":"ทหารไทย จำกัด (มหาชน)","imageUrl":"https://cpc.ais.co.th/CPC-FE-WEB/api/contents/upload/TTB_11-TTB-Logo.png"},{"bankAbbr":"UOB","installments":[{"installId":265,"installmentAbb":"0%  3 เดือน ( 3 M)"},{"installId":267,"installmentAbb":"0%  6 เดือน ( 6 M)"},{"installId":272,"installmentAbb":"0% 10 เดือน (10 M)"},{"installId":277,"installmentAbb":"0% 15 เดือน (15 M)"},{"installId":282,"installmentAbb":"0% 24 เดือน (24 M)"},{"installId":581,"installmentAbb":"0% 12 เดือน (12 M)"},{"installId":863,"installmentAbb":"0% 18 เดือน (18 M)"},{"installId":51828,"installmentAbb":"0%  36 เดือน (36 M)"}],"bankDescEn":"UNITED OVERSEAS BANK(THAI)PUBLIC COMPANY LIMITED","bankDescTh":"ยูโอบี จำกัด (มหาชน)","imageUrl":"https://cpc.ais.co.th/CPC-FE-WEB/api/contents/upload/UOB_UOB-bank.png"}]},{"cardType":"OTHER","method":"CC","banks":[{"bankAbbr":"ACS","installments":[{"installId":20,"installmentAbb":"0%  3 เดือน ( 3 M)"},{"installId":22,"installmentAbb":"0%  6 เดือน ( 6 M)"},{"installId":27,"installmentAbb":"0% 10 เดือน (10 M)"}],"bankDescEn":"Ayudlhya Card Services","bankDescTh":"อยุธยาคาร์ด เซอร์วิสเซส","imageUrl":"https://cpc.ais.co.th/CPC-FE-WEB/api/contents/upload/ACS_BAY03.png"},{"bankAbbr":"AEON","installments":[{"installId":294,"installmentAbb":"0% 10 เดือน (10 M)"},{"installId":51837,"installmentAbb":"0% 18 เดือน (18 M)"},{"installId":51941,"installmentAbb":"0.59% 20 เดือน (20M)"},{"installId":51961,"installmentAbb":"0.59% 12 เดือน (12M)"},{"installId":52001,"installmentAbb":"0.69% 24 เดือน (24 M)"}],"bankDescEn":"AEON THANA SINSAP (THAILAND) PCL.","bankDescTh":"บริษัทอิออนธนสินทรัพย์ (ไทยแลนด์) จำกัด (มหาชน)","imageUrl":"https://cpc.ais.co.th/CPC-FE-WEB/api/contents/upload/AEON_AEON-logo.png"},{"bankAbbr":"BAY","installments":[{"installId":38,"installmentAbb":"0%  3 เดือน ( 3 M)"},{"installId":41,"installmentAbb":"0%  6 เดือน ( 6 M)"},{"installId":47,"installmentAbb":"0% 10 เดือน (10 M)"}],"bankDescEn":"BANK OF AYUDHAYA PUBLIC COMPANY LIMITED","bankDescTh":"กรุงศรีอยุธยา จำกัด (มหาชน)","imageUrl":"https://cpc.ais.co.th/CPC-FE-WEB/api/contents/upload/BAY_BAY.png"},{"bankAbbr":"BBL","installments":[{"installId":60,"installmentAbb":"0% 4 เดือน (4 M)"},{"installId":65,"installmentAbb":"0%  6 เดือน ( 6 M)"},{"installId":71,"installmentAbb":"0% 10 เดือน (10 M)"}],"bankDescEn":"BANGKOK BANK PUBLIC COMPANY LIMITED","bankDescTh":"กรุงเทพ จำกัด (มหาชน)","imageUrl":"https://cpc.ais.co.th/CPC-FE-WEB/api/contents/upload/BBL_BBL.png"},{"bankAbbr":"CITI","installments":[{"installId":309,"installmentAbb":"0% 4 เดือน (4 M)"},{"installId":314,"installmentAbb":"0%  6 เดือน ( 6 M)"},{"installId":320,"installmentAbb":"0% 10 เดือน (10 M)"}],"bankDescEn":"CITIBANK N.A.","bankDescTh":"ซิตี้แบงก์","imageUrl":"https://cpc.ais.co.th/CPC-FE-WEB/api/contents/upload/CITI_CITI.png"},{"bankAbbr":"CITIREADY","installments":[{"installId":432,"installmentAbb":"0% 4 เดือน (4 M)"},{"installId":436,"installmentAbb":"0%  6 เดือน ( 6 M)"},{"installId":440,"installmentAbb":"0% 10 เดือน (10 M)"},{"installId":445,"installmentAbb":"0% 24 เดือน (24 M)"},{"installId":524,"installmentAbb":"0% 18 เดือน (18 M)"},{"installId":884,"installmentAbb":"0% 12 เดือน (12 M)"},{"installId":51883,"installmentAbb":"0% 30 เดือน (30M)"},{"installId":51886,"installmentAbb":"0%  40 เดือน (40 M)"}],"bankDescEn":"CITIBANK Ready","bankDescTh":"ซิตี้แบงก์ เรดดี้เครดิต","imageUrl":"https://cpc.ais.co.th/CPC-FE-WEB/api/contents/upload/CITIREADY_citibank02.jpg"},{"bankAbbr":"CT","installments":[{"installId":2,"installmentAbb":"0%  3 เดือน ( 3 M)"},{"installId":2,"installmentAbb":"0%  3 เดือน ( 3 M)"},{"installId":4,"installmentAbb":"0%  6 เดือน ( 6 M)"},{"installId":4,"installmentAbb":"0%  6 เดือน ( 6 M)"},{"installId":10,"installmentAbb":"0% 10 เดือน (10 M)"},{"installId":10,"installmentAbb":"0% 10 เดือน (10 M)"}],"bankDescEn":"Central","bankDescTh":"เซ็นทรัล","imageUrl":"https://cpc.ais.co.th/CPC-FE-WEB/api/contents/upload/CT_ct_logo.png"},{"bankAbbr":"FCC","installments":[{"installId":108,"installmentAbb":"0%  6 เดือน ( 6 M)"},{"installId":112,"installmentAbb":"0% 10 เดือน (10 M)"},{"installId":136,"installmentAbb":"0.89% 20 เดือน (20 M)"},{"installId":461,"installmentAbb":"0% 15 เดือน (15 M)"},{"installId":722,"installmentAbb":"0% 20 เดือน (20 M)"},{"installId":846,"installmentAbb":"0% 12 เดือน (12 M)"}],"bankDescEn":"Frist Choice Credit Card","bankDescTh":"บัตรเครดิต เฟิร์สช้อยส์","imageUrl":"https://cpc.ais.co.th/CPC-FE-WEB/api/contents/upload/FCC_fcc_logo.png"},{"bankAbbr":"KBNK","installments":[{"installId":350,"installmentAbb":"0% 4 เดือน (4 M)"},{"installId":355,"installmentAbb":"0%  6 เดือน ( 6 M)"},{"installId":361,"installmentAbb":"0% 10 เดือน (10 M)"},{"installId":874,"installmentAbb":"0% 12 เดือน (12 M)"},{"installId":876,"installmentAbb":"0% 18 เดือน (18 M)"},{"installId":878,"installmentAbb":"0% 24 เดือน (24 M)"},{"installId":51860,"installmentAbb":"0%  36 เดือน (36 M)"}],"bankDescEn":"KASIKORNBANK PUBLIC COMPANY LIMITED","bankDescTh":"กสิกรไทย จำกัด (มหาชน)","imageUrl":"https://cpc.ais.co.th/CPC-FE-WEB/api/contents/upload/KBNK_kBank.png"},{"bankAbbr":"KTB","installments":[{"installId":161,"installmentAbb":"0%  6 เดือน ( 6 M)"},{"installId":167,"installmentAbb":"0% 10 เดือน (10 M)"},{"installId":462,"installmentAbb":"0% 12 เดือน (12 M)"},{"installId":849,"installmentAbb":"0% 18 เดือน (18 M)"},{"installId":51765,"installmentAbb":"0.59% 20 เดือน (20M)"}],"bankDescEn":"KRUNG THAI BANK PUBLIC COMPANY LIMITED","bankDescTh":"กรุงไทย จำกัด (มหาชน)","imageUrl":"https://cpc.ais.co.th/CPC-FE-WEB/api/contents/upload/KTB_KTB.png"},{"bankAbbr":"NBNK","installments":[{"installId":373,"installmentAbb":"0% 4 เดือน (4 M)"},{"installId":378,"installmentAbb":"0%  6 เดือน ( 6 M)"},{"installId":384,"installmentAbb":"0% 10 เดือน (10 M)"},{"installId":395,"installmentAbb":"0% 20 เดือน (20 M)"},{"installId":397,"installmentAbb":"0% 24 เดือน (24 M)"}],"bankDescEn":"THANACHART BANK PUBLIC COMPANY LIMITED","bankDescTh":"ธนชาต จำกัด(มหาชน)","imageUrl":"https://cpc.ais.co.th/CPC-FE-WEB/api/contents/upload/NBNK_65-NBNK-Logo.png"},{"bankAbbr":"SCB","installments":[{"installId":191,"installmentAbb":"0% 4 เดือน (4 M)"},{"installId":196,"installmentAbb":"0%  6 เดือน ( 6 M)"},{"installId":202,"installmentAbb":"0% 10 เดือน (10 M)"},{"installId":214,"installmentAbb":"0% 24 เดือน (24 M)"},{"installId":463,"installmentAbb":"0% 18 เดือน (18 M)"},{"installId":854,"installmentAbb":"0% 12 เดือน (12 M)"}],"bankDescEn":"SIAM COMMERCIAL BANK PUBLIC COMPANY LIMITED","bankDescTh":"ไทยพาณิชย์ จำกัด (มหาชน)","imageUrl":"https://cpc.ais.co.th/CPC-FE-WEB/api/contents/upload/SCB_SCB.png"},{"bankAbbr":"TCS","installments":[{"installId":239,"installmentAbb":"0%  3 เดือน ( 3 M)"},{"installId":239,"installmentAbb":"0%  3 เดือน ( 3 M)"},{"installId":241,"installmentAbb":"0%  6 เดือน ( 6 M)"},{"installId":241,"installmentAbb":"0%  6 เดือน ( 6 M)"},{"installId":246,"installmentAbb":"0% 10 เดือน (10 M)"},{"installId":246,"installmentAbb":"0% 10 เดือน (10 M)"}],"bankDescEn":"TESCO LOTUS VISA CARD","bankDescTh":"บัตรเครดิต เทสโก้ โลตัส วีซ่า","imageUrl":"https://cpc.ais.co.th/CPC-FE-WEB/api/contents/upload/TCS_TescoLotus-CreditCard.png"},{"bankAbbr":"TMB","installments":[{"installId":981,"installmentAbb":"0% 4 เดือน (4 M)"},{"installId":982,"installmentAbb":"0% 10 เดือน (10 M)"},{"installId":51814,"installmentAbb":"0%  6 เดือน ( 6 M)"},{"installId":51818,"installmentAbb":"0% 20 เดือน (20 M)"},{"installId":51819,"installmentAbb":"0% 24 เดือน (24 M)"}],"bankDescEn":"THAI MILITARY BANK PUBLIC COMPANY LIMITED","bankDescTh":"ทหารไทย จำกัด (มหาชน)","imageUrl":"https://cpc.ais.co.th/CPC-FE-WEB/api/contents/upload/TTB_11-TTB-Logo.png"},{"bankAbbr":"UOB","installments":[{"installId":265,"installmentAbb":"0%  3 เดือน ( 3 M)"},{"installId":267,"installmentAbb":"0%  6 เดือน ( 6 M)"},{"installId":272,"installmentAbb":"0% 10 เดือน (10 M)"},{"installId":277,"installmentAbb":"0% 15 เดือน (15 M)"},{"installId":282,"installmentAbb":"0% 24 เดือน (24 M)"},{"installId":581,"installmentAbb":"0% 12 เดือน (12 M)"},{"installId":863,"installmentAbb":"0% 18 เดือน (18 M)"},{"installId":51828,"installmentAbb":"0%  36 เดือน (36 M)"}],"bankDescEn":"UNITED OVERSEAS BANK(THAI)PUBLIC COMPANY LIMITED","bankDescTh":"ยูโอบี จำกัด (มหาชน)","imageUrl":"https://cpc.ais.co.th/CPC-FE-WEB/api/contents/upload/UOB_UOB-bank.png"}]},{"cardType":"VISA","method":"CC","banks":[{"bankAbbr":"ACS","installments":[{"installId":20,"installmentAbb":"0%  3 เดือน ( 3 M)"},{"installId":22,"installmentAbb":"0%  6 เดือน ( 6 M)"},{"installId":27,"installmentAbb":"0% 10 เดือน (10 M)"}],"bankDescEn":"Ayudlhya Card Services","bankDescTh":"อยุธยาคาร์ด เซอร์วิสเซส","imageUrl":"https://cpc.ais.co.th/CPC-FE-WEB/api/contents/upload/ACS_BAY03.png"},{"bankAbbr":"AEON","installments":[{"installId":294,"installmentAbb":"0% 10 เดือน (10 M)"},{"installId":51837,"installmentAbb":"0% 18 เดือน (18 M)"},{"installId":51941,"installmentAbb":"0.59% 20 เดือน (20M)"},{"installId":51961,"installmentAbb":"0.59% 12 เดือน (12M)"},{"installId":52001,"installmentAbb":"0.69% 24 เดือน (24 M)"}],"bankDescEn":"AEON THANA SINSAP (THAILAND) PCL.","bankDescTh":"บริษัทอิออนธนสินทรัพย์ (ไทยแลนด์) จำกัด (มหาชน)","imageUrl":"https://cpc.ais.co.th/CPC-FE-WEB/api/contents/upload/AEON_AEON-logo.png"},{"bankAbbr":"BAY","installments":[{"installId":38,"installmentAbb":"0%  3 เดือน ( 3 M)"},{"installId":41,"installmentAbb":"0%  6 เดือน ( 6 M)"},{"installId":47,"installmentAbb":"0% 10 เดือน (10 M)"}],"bankDescEn":"BANK OF AYUDHAYA PUBLIC COMPANY LIMITED","bankDescTh":"กรุงศรีอยุธยา จำกัด (มหาชน)","imageUrl":"https://cpc.ais.co.th/CPC-FE-WEB/api/contents/upload/BAY_BAY.png"},{"bankAbbr":"BBL","installments":[{"installId":60,"installmentAbb":"0% 4 เดือน (4 M)"},{"installId":65,"installmentAbb":"0%  6 เดือน ( 6 M)"},{"installId":71,"installmentAbb":"0% 10 เดือน (10 M)"}],"bankDescEn":"BANGKOK BANK PUBLIC COMPANY LIMITED","bankDescTh":"กรุงเทพ จำกัด (มหาชน)","imageUrl":"https://cpc.ais.co.th/CPC-FE-WEB/api/contents/upload/BBL_BBL.png"},{"bankAbbr":"CITI","installments":[{"installId":309,"installmentAbb":"0% 4 เดือน (4 M)"},{"installId":314,"installmentAbb":"0%  6 เดือน ( 6 M)"},{"installId":320,"installmentAbb":"0% 10 เดือน (10 M)"}],"bankDescEn":"CITIBANK N.A.","bankDescTh":"ซิตี้แบงก์","imageUrl":"https://cpc.ais.co.th/CPC-FE-WEB/api/contents/upload/CITI_CITI.png"},{"bankAbbr":"CITIREADY","installments":[{"installId":432,"installmentAbb":"0% 4 เดือน (4 M)"},{"installId":436,"installmentAbb":"0%  6 เดือน ( 6 M)"},{"installId":440,"installmentAbb":"0% 10 เดือน (10 M)"},{"installId":445,"installmentAbb":"0% 24 เดือน (24 M)"},{"installId":524,"installmentAbb":"0% 18 เดือน (18 M)"},{"installId":884,"installmentAbb":"0% 12 เดือน (12 M)"},{"installId":51883,"installmentAbb":"0% 30 เดือน (30M)"},{"installId":51886,"installmentAbb":"0%  40 เดือน (40 M)"}],"bankDescEn":"CITIBANK Ready","bankDescTh":"ซิตี้แบงก์ เรดดี้เครดิต","imageUrl":"https://cpc.ais.co.th/CPC-FE-WEB/api/contents/upload/CITIREADY_citibank02.jpg"},{"bankAbbr":"CT","installments":[{"installId":2,"installmentAbb":"0%  3 เดือน ( 3 M)"},{"installId":2,"installmentAbb":"0%  3 เดือน ( 3 M)"},{"installId":4,"installmentAbb":"0%  6 เดือน ( 6 M)"},{"installId":4,"installmentAbb":"0%  6 เดือน ( 6 M)"},{"installId":10,"installmentAbb":"0% 10 เดือน (10 M)"},{"installId":10,"installmentAbb":"0% 10 เดือน (10 M)"}],"bankDescEn":"Central","bankDescTh":"เซ็นทรัล","imageUrl":"https://cpc.ais.co.th/CPC-FE-WEB/api/contents/upload/CT_ct_logo.png"},{"bankAbbr":"FCC","installments":[{"installId":108,"installmentAbb":"0%  6 เดือน ( 6 M)"},{"installId":112,"installmentAbb":"0% 10 เดือน (10 M)"},{"installId":136,"installmentAbb":"0.89% 20 เดือน (20 M)"},{"installId":461,"installmentAbb":"0% 15 เดือน (15 M)"},{"installId":722,"installmentAbb":"0% 20 เดือน (20 M)"},{"installId":846,"installmentAbb":"0% 12 เดือน (12 M)"}],"bankDescEn":"Frist Choice Credit Card","bankDescTh":"บัตรเครดิต เฟิร์สช้อยส์","imageUrl":"https://cpc.ais.co.th/CPC-FE-WEB/api/contents/upload/FCC_fcc_logo.png"},{"bankAbbr":"KBNK","installments":[{"installId":350,"installmentAbb":"0% 4 เดือน (4 M)"},{"installId":355,"installmentAbb":"0%  6 เดือน ( 6 M)"},{"installId":361,"installmentAbb":"0% 10 เดือน (10 M)"},{"installId":874,"installmentAbb":"0% 12 เดือน (12 M)"},{"installId":876,"installmentAbb":"0% 18 เดือน (18 M)"},{"installId":878,"installmentAbb":"0% 24 เดือน (24 M)"},{"installId":51860,"installmentAbb":"0%  36 เดือน (36 M)"}],"bankDescEn":"KASIKORNBANK PUBLIC COMPANY LIMITED","bankDescTh":"กสิกรไทย จำกัด (มหาชน)","imageUrl":"https://cpc.ais.co.th/CPC-FE-WEB/api/contents/upload/KBNK_kBank.png"},{"bankAbbr":"KTB","installments":[{"installId":161,"installmentAbb":"0%  6 เดือน ( 6 M)"},{"installId":167,"installmentAbb":"0% 10 เดือน (10 M)"},{"installId":462,"installmentAbb":"0% 12 เดือน (12 M)"},{"installId":849,"installmentAbb":"0% 18 เดือน (18 M)"},{"installId":51765,"installmentAbb":"0.59% 20 เดือน (20M)"}],"bankDescEn":"KRUNG THAI BANK PUBLIC COMPANY LIMITED","bankDescTh":"กรุงไทย จำกัด (มหาชน)","imageUrl":"https://cpc.ais.co.th/CPC-FE-WEB/api/contents/upload/KTB_KTB.png"},{"bankAbbr":"NBNK","installments":[{"installId":373,"installmentAbb":"0% 4 เดือน (4 M)"},{"installId":378,"installmentAbb":"0%  6 เดือน ( 6 M)"},{"installId":384,"installmentAbb":"0% 10 เดือน (10 M)"},{"installId":395,"installmentAbb":"0% 20 เดือน (20 M)"},{"installId":397,"installmentAbb":"0% 24 เดือน (24 M)"}],"bankDescEn":"THANACHART BANK PUBLIC COMPANY LIMITED","bankDescTh":"ธนชาต จำกัด(มหาชน)","imageUrl":"https://cpc.ais.co.th/CPC-FE-WEB/api/contents/upload/NBNK_65-NBNK-Logo.png"},{"bankAbbr":"SCB","installments":[{"installId":191,"installmentAbb":"0% 4 เดือน (4 M)"},{"installId":196,"installmentAbb":"0%  6 เดือน ( 6 M)"},{"installId":202,"installmentAbb":"0% 10 เดือน (10 M)"},{"installId":214,"installmentAbb":"0% 24 เดือน (24 M)"},{"installId":463,"installmentAbb":"0% 18 เดือน (18 M)"},{"installId":854,"installmentAbb":"0% 12 เดือน (12 M)"}],"bankDescEn":"SIAM COMMERCIAL BANK PUBLIC COMPANY LIMITED","bankDescTh":"ไทยพาณิชย์ จำกัด (มหาชน)","imageUrl":"https://cpc.ais.co.th/CPC-FE-WEB/api/contents/upload/SCB_SCB.png"},{"bankAbbr":"TCS","installments":[{"installId":239,"installmentAbb":"0%  3 เดือน ( 3 M)"},{"installId":239,"installmentAbb":"0%  3 เดือน ( 3 M)"},{"installId":241,"installmentAbb":"0%  6 เดือน ( 6 M)"},{"installId":241,"installmentAbb":"0%  6 เดือน ( 6 M)"},{"installId":246,"installmentAbb":"0% 10 เดือน (10 M)"},{"installId":246,"installmentAbb":"0% 10 เดือน (10 M)"}],"bankDescEn":"TESCO LOTUS VISA CARD","bankDescTh":"บัตรเครดิต เทสโก้ โลตัส วีซ่า","imageUrl":"https://cpc.ais.co.th/CPC-FE-WEB/api/contents/upload/TCS_TescoLotus-CreditCard.png"},{"bankAbbr":"TMB","installments":[{"installId":981,"installmentAbb":"0% 4 เดือน (4 M)"},{"installId":982,"installmentAbb":"0% 10 เดือน (10 M)"},{"installId":51814,"installmentAbb":"0%  6 เดือน ( 6 M)"},{"installId":51818,"installmentAbb":"0% 20 เดือน (20 M)"},{"installId":51819,"installmentAbb":"0% 24 เดือน (24 M)"}],"bankDescEn":"THAI MILITARY BANK PUBLIC COMPANY LIMITED","bankDescTh":"ทหารไทย จำกัด (มหาชน)","imageUrl":"https://cpc.ais.co.th/CPC-FE-WEB/api/contents/upload/TTB_11-TTB-Logo.png"},{"bankAbbr":"UOB","installments":[{"installId":265,"installmentAbb":"0%  3 เดือน ( 3 M)"},{"installId":267,"installmentAbb":"0%  6 เดือน ( 6 M)"},{"installId":272,"installmentAbb":"0% 10 เดือน (10 M)"},{"installId":277,"installmentAbb":"0% 15 เดือน (15 M)"},{"installId":282,"installmentAbb":"0% 24 เดือน (24 M)"},{"installId":581,"installmentAbb":"0% 12 เดือน (12 M)"},{"installId":863,"installmentAbb":"0% 18 เดือน (18 M)"},{"installId":51828,"installmentAbb":"0%  36 เดือน (36 M)"}],"bankDescEn":"UNITED OVERSEAS BANK(THAI)PUBLIC COMPANY LIMITED","bankDescTh":"ยูโอบี จำกัด (มหาชน)","imageUrl":"https://cpc.ais.co.th/CPC-FE-WEB/api/contents/upload/UOB_UOB-bank.png"}]},{"cardType":"MASTER","method":"CC","banks":[{"bankAbbr":"ACS","bankDescEn":"Ayudlhya Card Services","bankDescTh":"อยุธยาคาร์ด เซอร์วิสเซส","imageUrl":"https://cpc.ais.co.th/CPC-FE-WEB/api/contents/upload/ACS_BAY03.png","installments":[]},{"bankAbbr":"BAY","bankDescEn":"BANK OF AYUDHAYA PUBLIC COMPANY LIMITED","bankDescTh":"กรุงศรีอยุธยา จำกัด (มหาชน)","imageUrl":"https://cpc.ais.co.th/CPC-FE-WEB/api/contents/upload/BAY_BAY.png","installments":[]},{"bankAbbr":"BBL","bankDescEn":"BANGKOK BANK PUBLIC COMPANY LIMITED","bankDescTh":"กรุงเทพ จำกัด (มหาชน)","imageUrl":"https://cpc.ais.co.th/CPC-FE-WEB/api/contents/upload/BBL_BBL.png","installments":[]},{"bankAbbr":"CITI","bankDescEn":"CITIBANK N.A.","bankDescTh":"ซิตี้แบงก์","imageUrl":"https://cpc.ais.co.th/CPC-FE-WEB/api/contents/upload/CITI_CITI.png","installments":[]},{"bankAbbr":"CT","bankDescEn":"Central","bankDescTh":"เซ็นทรัล","imageUrl":"https://cpc.ais.co.th/CPC-FE-WEB/api/contents/upload/CT_Central.png","installments":[]},{"bankAbbr":"CT","bankDescEn":"Central","bankDescTh":"เซ็นทรัล","imageUrl":"https://cpc.ais.co.th/CPC-FE-WEB/api/contents/upload/CT_ct_logo.png","installments":[]},{"bankAbbr":"FCC","bankDescEn":"Frist Choice Credit Card","bankDescTh":"บัตรเครดิต เฟิร์สช้อยส์","imageUrl":"https://cpc.ais.co.th/CPC-FE-WEB/api/contents/upload/FCC_fcc_logo.png","installments":[]},{"bankAbbr":"KBNK","bankDescEn":"KASIKORNBANK PUBLIC COMPANY LIMITED","bankDescTh":"กสิกรไทย จำกัด (มหาชน)","imageUrl":"https://cpc.ais.co.th/CPC-FE-WEB/api/contents/upload/KBNK_kBank.png","installments":[]},{"bankAbbr":"KTB","bankDescEn":"KRUNG THAI BANK PUBLIC COMPANY LIMITED","bankDescTh":"กรุงไทย จำกัด (มหาชน)","imageUrl":"https://cpc.ais.co.th/CPC-FE-WEB/api/contents/upload/KTB_KTB.png","installments":[]},{"bankAbbr":"NBNK","bankDescEn":"THANACHART BANK PUBLIC COMPANY LIMITED","bankDescTh":"ธนชาต จำกัด(มหาชน)","imageUrl":"https://cpc.ais.co.th/CPC-FE-WEB/api/contents/upload/NBNK_65-NBNK-Logo.png","installments":[]},{"bankAbbr":"SCB","bankDescEn":"SIAM COMMERCIAL BANK PUBLIC COMPANY LIMITED","bankDescTh":"ไทยพาณิชย์ จำกัด (มหาชน)","imageUrl":"https://cpc.ais.co.th/CPC-FE-WEB/api/contents/upload/SCB_SCB.png","installments":[]},{"bankAbbr":"TCS","bankDescEn":"TESCO LOTUS VISA CARD","bankDescTh":"บัตรเครดิต เทสโก้ โลตัส วีซ่า","imageUrl":"https://cpc.ais.co.th/CPC-FE-WEB/api/contents/upload/TCS_444-TCS-Logo.png","installments":[]},{"bankAbbr":"TCS","bankDescEn":"TESCO LOTUS VISA CARD","bankDescTh":"บัตรเครดิต เทสโก้ โลตัส วีซ่า","imageUrl":"https://cpc.ais.co.th/CPC-FE-WEB/api/contents/upload/TCS_TescoLotus-CreditCard.png","installments":[]},{"bankAbbr":"UOB","bankDescEn":"UNITED OVERSEAS BANK(THAI)PUBLIC COMPANY LIMITED","bankDescTh":"ยูโอบี จำกัด (มหาชน)","imageUrl":"https://cpc.ais.co.th/CPC-FE-WEB/api/contents/upload/UOB_UOB-bank.png","installments":[]}]},{"cardType":"OTHER","method":"CC","banks":[{"bankAbbr":"ACS","bankDescEn":"Ayudlhya Card Services","bankDescTh":"อยุธยาคาร์ด เซอร์วิสเซส","imageUrl":"https://cpc.ais.co.th/CPC-FE-WEB/api/contents/upload/ACS_BAY03.png","installments":[]},{"bankAbbr":"BAY","bankDescEn":"BANK OF AYUDHAYA PUBLIC COMPANY LIMITED","bankDescTh":"กรุงศรีอยุธยา จำกัด (มหาชน)","imageUrl":"https://cpc.ais.co.th/CPC-FE-WEB/api/contents/upload/BAY_BAY.png","installments":[]},{"bankAbbr":"BBL","bankDescEn":"BANGKOK BANK PUBLIC COMPANY LIMITED","bankDescTh":"กรุงเทพ จำกัด (มหาชน)","imageUrl":"https://cpc.ais.co.th/CPC-FE-WEB/api/contents/upload/BBL_BBL.png","installments":[]},{"bankAbbr":"CITI","bankDescEn":"CITIBANK N.A.","bankDescTh":"ซิตี้แบงก์","imageUrl":"https://cpc.ais.co.th/CPC-FE-WEB/api/contents/upload/CITI_CITI.png","installments":[]},{"bankAbbr":"CT","bankDescEn":"Central","bankDescTh":"เซ็นทรัล","imageUrl":"https://cpc.ais.co.th/CPC-FE-WEB/api/contents/upload/CT_Central.png","installments":[]},{"bankAbbr":"CT","bankDescEn":"Central","bankDescTh":"เซ็นทรัล","imageUrl":"https://cpc.ais.co.th/CPC-FE-WEB/api/contents/upload/CT_ct_logo.png","installments":[]},{"bankAbbr":"FCC","bankDescEn":"Frist Choice Credit Card","bankDescTh":"บัตรเครดิต เฟิร์สช้อยส์","imageUrl":"https://cpc.ais.co.th/CPC-FE-WEB/api/contents/upload/FCC_fcc_logo.png","installments":[]},{"bankAbbr":"KBNK","bankDescEn":"KASIKORNBANK PUBLIC COMPANY LIMITED","bankDescTh":"กสิกรไทย จำกัด (มหาชน)","imageUrl":"https://cpc.ais.co.th/CPC-FE-WEB/api/contents/upload/KBNK_kBank.png","installments":[]},{"bankAbbr":"KTB","bankDescEn":"KRUNG THAI BANK PUBLIC COMPANY LIMITED","bankDescTh":"กรุงไทย จำกัด (มหาชน)","imageUrl":"https://cpc.ais.co.th/CPC-FE-WEB/api/contents/upload/KTB_KTB.png","installments":[]},{"bankAbbr":"NBNK","bankDescEn":"THANACHART BANK PUBLIC COMPANY LIMITED","bankDescTh":"ธนชาต จำกัด(มหาชน)","imageUrl":"https://cpc.ais.co.th/CPC-FE-WEB/api/contents/upload/NBNK_65-NBNK-Logo.png","installments":[]},{"bankAbbr":"SCB","bankDescEn":"SIAM COMMERCIAL BANK PUBLIC COMPANY LIMITED","bankDescTh":"ไทยพาณิชย์ จำกัด (มหาชน)","imageUrl":"https://cpc.ais.co.th/CPC-FE-WEB/api/contents/upload/SCB_SCB.png","installments":[]},{"bankAbbr":"TCS","bankDescEn":"TESCO LOTUS VISA CARD","bankDescTh":"บัตรเครดิต เทสโก้ โลตัส วีซ่า","imageUrl":"https://cpc.ais.co.th/CPC-FE-WEB/api/contents/upload/TCS_444-TCS-Logo.png","installments":[]},{"bankAbbr":"TCS","bankDescEn":"TESCO LOTUS VISA CARD","bankDescTh":"บัตรเครดิต เทสโก้ โลตัส วีซ่า","imageUrl":"https://cpc.ais.co.th/CPC-FE-WEB/api/contents/upload/TCS_TescoLotus-CreditCard.png","installments":[]},{"bankAbbr":"UOB","bankDescEn":"UNITED OVERSEAS BANK(THAI)PUBLIC COMPANY LIMITED","bankDescTh":"ยูโอบี จำกัด (มหาชน)","imageUrl":"https://cpc.ais.co.th/CPC-FE-WEB/api/contents/upload/UOB_UOB-bank.png","installments":[]}]},{"cardType":"VISA","method":"CC","banks":[{"bankAbbr":"ACS","bankDescEn":"Ayudlhya Card Services","bankDescTh":"อยุธยาคาร์ด เซอร์วิสเซส","imageUrl":"https://cpc.ais.co.th/CPC-FE-WEB/api/contents/upload/ACS_BAY03.png","installments":[]},{"bankAbbr":"BAY","bankDescEn":"BANK OF AYUDHAYA PUBLIC COMPANY LIMITED","bankDescTh":"กรุงศรีอยุธยา จำกัด (มหาชน)","imageUrl":"https://cpc.ais.co.th/CPC-FE-WEB/api/contents/upload/BAY_BAY.png","installments":[]},{"bankAbbr":"BBL","bankDescEn":"BANGKOK BANK PUBLIC COMPANY LIMITED","bankDescTh":"กรุงเทพ จำกัด (มหาชน)","imageUrl":"https://cpc.ais.co.th/CPC-FE-WEB/api/contents/upload/BBL_BBL.png","installments":[]},{"bankAbbr":"CITI","bankDescEn":"CITIBANK N.A.","bankDescTh":"ซิตี้แบงก์","imageUrl":"https://cpc.ais.co.th/CPC-FE-WEB/api/contents/upload/CITI_CITI.png","installments":[]},{"bankAbbr":"CT","bankDescEn":"Central","bankDescTh":"เซ็นทรัล","imageUrl":"https://cpc.ais.co.th/CPC-FE-WEB/api/contents/upload/CT_Central.png","installments":[]},{"bankAbbr":"CT","bankDescEn":"Central","bankDescTh":"เซ็นทรัล","imageUrl":"https://cpc.ais.co.th/CPC-FE-WEB/api/contents/upload/CT_ct_logo.png","installments":[]},{"bankAbbr":"FCC","bankDescEn":"Frist Choice Credit Card","bankDescTh":"บัตรเครดิต เฟิร์สช้อยส์","imageUrl":"https://cpc.ais.co.th/CPC-FE-WEB/api/contents/upload/FCC_fcc_logo.png","installments":[]},{"bankAbbr":"KBNK","bankDescEn":"KASIKORNBANK PUBLIC COMPANY LIMITED","bankDescTh":"กสิกรไทย จำกัด (มหาชน)","imageUrl":"https://cpc.ais.co.th/CPC-FE-WEB/api/contents/upload/KBNK_kBank.png","installments":[]},{"bankAbbr":"KTB","bankDescEn":"KRUNG THAI BANK PUBLIC COMPANY LIMITED","bankDescTh":"กรุงไทย จำกัด (มหาชน)","imageUrl":"https://cpc.ais.co.th/CPC-FE-WEB/api/contents/upload/KTB_KTB.png","installments":[]},{"bankAbbr":"NBNK","bankDescEn":"THANACHART BANK PUBLIC COMPANY LIMITED","bankDescTh":"ธนชาต จำกัด(มหาชน)","imageUrl":"https://cpc.ais.co.th/CPC-FE-WEB/api/contents/upload/NBNK_65-NBNK-Logo.png","installments":[]},{"bankAbbr":"SCB","bankDescEn":"SIAM COMMERCIAL BANK PUBLIC COMPANY LIMITED","bankDescTh":"ไทยพาณิชย์ จำกัด (มหาชน)","imageUrl":"https://cpc.ais.co.th/CPC-FE-WEB/api/contents/upload/SCB_SCB.png","installments":[]},{"bankAbbr":"TCS","bankDescEn":"TESCO LOTUS VISA CARD","bankDescTh":"บัตรเครดิต เทสโก้ โลตัส วีซ่า","imageUrl":"https://cpc.ais.co.th/CPC-FE-WEB/api/contents/upload/TCS_444-TCS-Logo.png","installments":[]},{"bankAbbr":"TCS","bankDescEn":"TESCO LOTUS VISA CARD","bankDescTh":"บัตรเครดิต เทสโก้ โลตัส วีซ่า","imageUrl":"https://cpc.ais.co.th/CPC-FE-WEB/api/contents/upload/TCS_TescoLotus-CreditCard.png","installments":[]},{"bankAbbr":"UOB","bankDescEn":"UNITED OVERSEAS BANK(THAI)PUBLIC COMPANY LIMITED","bankDescTh":"ยูโอบี จำกัด (มหาชน)","imageUrl":"https://cpc.ais.co.th/CPC-FE-WEB/api/contents/upload/UOB_UOB-bank.png","installments":[]}]},{"method":"CA","banks":[]},{"method":"CC","banks":[]},{"method":"CI","banks":[]},{"method":"CP","banks":[]},{"method":"DC","banks":[]},{"method":"GV","banks":[]},{"method":"PB","banks":[]},{"method":"QP","banks":[]},{"method":"RL","banks":[]},{"method":"V1","banks":[]},{"method":"V2","banks":[]}],"freegoods":[],"privileges":[],"criterias":[],"channels":[{"saleChannel":"MIN","province":"ALL"},{"saleChannel":"ACC","province":"ALL"},{"saleChannel":"BRN","province":"ALL"}],"tradeName":"AWN PRODUCT_FULL PAYMENT AND INSTALLMENT_APPLE","campaignName":"Handset Trading","saleType":"SALE","startDate":"2021-06-30T17:00:00Z","endDate":"2025-12-31T16:59:00Z"},{"tradeNo":"TP22050275","payAdvances":[],"discounts":[],"payments":[{"cardType":"MASTER","method":"CC","banks":[{"bankAbbr":"ACS","installments":[{"installId":20,"installmentAbb":"0%  3 เดือน ( 3 M)"},{"installId":22,"installmentAbb":"0%  6 เดือน ( 6 M)"},{"installId":27,"installmentAbb":"0% 10 เดือน (10 M)"}],"bankDescEn":"Ayudlhya Card Services","bankDescTh":"อยุธยาคาร์ด เซอร์วิสเซส","imageUrl":"https://cpc.ais.co.th/CPC-FE-WEB/api/contents/upload/ACS_BAY03.png"},{"bankAbbr":"AEON","installments":[{"installId":294,"installmentAbb":"0% 10 เดือน (10 M)"},{"installId":51837,"installmentAbb":"0% 18 เดือน (18 M)"},{"installId":51941,"installmentAbb":"0.59% 20 เดือน (20M)"},{"installId":51961,"installmentAbb":"0.59% 12 เดือน (12M)"},{"installId":52001,"installmentAbb":"0.69% 24 เดือน (24 M)"}],"bankDescEn":"AEON THANA SINSAP (THAILAND) PCL.","bankDescTh":"บริษัทอิออนธนสินทรัพย์ (ไทยแลนด์) จำกัด (มหาชน)","imageUrl":"https://cpc.ais.co.th/CPC-FE-WEB/api/contents/upload/AEON_AEON-logo.png"},{"bankAbbr":"BAY","installments":[{"installId":38,"installmentAbb":"0%  3 เดือน ( 3 M)"},{"installId":41,"installmentAbb":"0%  6 เดือน ( 6 M)"},{"installId":47,"installmentAbb":"0% 10 เดือน (10 M)"}],"bankDescEn":"BANK OF AYUDHAYA PUBLIC COMPANY LIMITED","bankDescTh":"กรุงศรีอยุธยา จำกัด (มหาชน)","imageUrl":"https://cpc.ais.co.th/CPC-FE-WEB/api/contents/upload/BAY_BAY.png"},{"bankAbbr":"BBL","installments":[{"installId":60,"installmentAbb":"0% 4 เดือน (4 M)"},{"installId":65,"installmentAbb":"0%  6 เดือน ( 6 M)"},{"installId":71,"installmentAbb":"0% 10 เดือน (10 M)"}],"bankDescEn":"BANGKOK BANK PUBLIC COMPANY LIMITED","bankDescTh":"กรุงเทพ จำกัด (มหาชน)","imageUrl":"https://cpc.ais.co.th/CPC-FE-WEB/api/contents/upload/BBL_BBL.png"},{"bankAbbr":"CITI","installments":[{"installId":309,"installmentAbb":"0% 4 เดือน (4 M)"},{"installId":314,"installmentAbb":"0%  6 เดือน ( 6 M)"},{"installId":320,"installmentAbb":"0% 10 เดือน (10 M)"}],"bankDescEn":"CITIBANK N.A.","bankDescTh":"ซิตี้แบงก์","imageUrl":"https://cpc.ais.co.th/CPC-FE-WEB/api/contents/upload/CITI_CITI.png"},{"bankAbbr":"CITIREADY","installments":[{"installId":432,"installmentAbb":"0% 4 เดือน (4 M)"},{"installId":436,"installmentAbb":"0%  6 เดือน ( 6 M)"},{"installId":440,"installmentAbb":"0% 10 เดือน (10 M)"},{"installId":445,"installmentAbb":"0% 24 เดือน (24 M)"},{"installId":524,"installmentAbb":"0% 18 เดือน (18 M)"},{"installId":884,"installmentAbb":"0% 12 เดือน (12 M)"},{"installId":51883,"installmentAbb":"0% 30 เดือน (30M)"},{"installId":51886,"installmentAbb":"0%  40 เดือน (40 M)"}],"bankDescEn":"CITIBANK Ready","bankDescTh":"ซิตี้แบงก์ เรดดี้เครดิต","imageUrl":"https://cpc.ais.co.th/CPC-FE-WEB/api/contents/upload/CITIREADY_citibank02.jpg"},{"bankAbbr":"CT","installments":[{"installId":2,"installmentAbb":"0%  3 เดือน ( 3 M)"},{"installId":2,"installmentAbb":"0%  3 เดือน ( 3 M)"},{"installId":4,"installmentAbb":"0%  6 เดือน ( 6 M)"},{"installId":4,"installmentAbb":"0%  6 เดือน ( 6 M)"},{"installId":10,"installmentAbb":"0% 10 เดือน (10 M)"},{"installId":10,"installmentAbb":"0% 10 เดือน (10 M)"}],"bankDescEn":"Central","bankDescTh":"เซ็นทรัล","imageUrl":"https://cpc.ais.co.th/CPC-FE-WEB/api/contents/upload/CT_ct_logo.png"},{"bankAbbr":"FCC","installments":[{"installId":108,"installmentAbb":"0%  6 เดือน ( 6 M)"},{"installId":112,"installmentAbb":"0% 10 เดือน (10 M)"},{"installId":136,"installmentAbb":"0.89% 20 เดือน (20 M)"},{"installId":461,"installmentAbb":"0% 15 เดือน (15 M)"},{"installId":722,"installmentAbb":"0% 20 เดือน (20 M)"},{"installId":846,"installmentAbb":"0% 12 เดือน (12 M)"}],"bankDescEn":"Frist Choice Credit Card","bankDescTh":"บัตรเครดิต เฟิร์สช้อยส์","imageUrl":"https://cpc.ais.co.th/CPC-FE-WEB/api/contents/upload/FCC_fcc_logo.png"},{"bankAbbr":"KBNK","installments":[{"installId":350,"installmentAbb":"0% 4 เดือน (4 M)"},{"installId":355,"installmentAbb":"0%  6 เดือน ( 6 M)"},{"installId":361,"installmentAbb":"0% 10 เดือน (10 M)"},{"installId":874,"installmentAbb":"0% 12 เดือน (12 M)"},{"installId":876,"installmentAbb":"0% 18 เดือน (18 M)"},{"installId":878,"installmentAbb":"0% 24 เดือน (24 M)"},{"installId":51860,"installmentAbb":"0%  36 เดือน (36 M)"}],"bankDescEn":"KASIKORNBANK PUBLIC COMPANY LIMITED","bankDescTh":"กสิกรไทย จำกัด (มหาชน)","imageUrl":"https://cpc.ais.co.th/CPC-FE-WEB/api/contents/upload/KBNK_kBank.png"},{"bankAbbr":"KTB","installments":[{"installId":161,"installmentAbb":"0%  6 เดือน ( 6 M)"},{"installId":167,"installmentAbb":"0% 10 เดือน (10 M)"},{"installId":462,"installmentAbb":"0% 12 เดือน (12 M)"},{"installId":849,"installmentAbb":"0% 18 เดือน (18 M)"},{"installId":51765,"installmentAbb":"0.59% 20 เดือน (20M)"}],"bankDescEn":"KRUNG THAI BANK PUBLIC COMPANY LIMITED","bankDescTh":"กรุงไทย จำกัด (มหาชน)","imageUrl":"https://cpc.ais.co.th/CPC-FE-WEB/api/contents/upload/KTB_KTB.png"},{"bankAbbr":"NBNK","installments":[{"installId":373,"installmentAbb":"0% 4 เดือน (4 M)"},{"installId":378,"installmentAbb":"0%  6 เดือน ( 6 M)"},{"installId":384,"installmentAbb":"0% 10 เดือน (10 M)"},{"installId":395,"installmentAbb":"0% 20 เดือน (20 M)"},{"installId":397,"installmentAbb":"0% 24 เดือน (24 M)"}],"bankDescEn":"THANACHART BANK PUBLIC COMPANY LIMITED","bankDescTh":"ธนชาต จำกัด(มหาชน)","imageUrl":"https://cpc.ais.co.th/CPC-FE-WEB/api/contents/upload/NBNK_65-NBNK-Logo.png"},{"bankAbbr":"SCB","installments":[{"installId":191,"installmentAbb":"0% 4 เดือน (4 M)"},{"installId":196,"installmentAbb":"0%  6 เดือน ( 6 M)"},{"installId":202,"installmentAbb":"0% 10 เดือน (10 M)"},{"installId":214,"installmentAbb":"0% 24 เดือน (24 M)"},{"installId":463,"installmentAbb":"0% 18 เดือน (18 M)"},{"installId":854,"installmentAbb":"0% 12 เดือน (12 M)"}],"bankDescEn":"SIAM COMMERCIAL BANK PUBLIC COMPANY LIMITED","bankDescTh":"ไทยพาณิชย์ จำกัด (มหาชน)","imageUrl":"https://cpc.ais.co.th/CPC-FE-WEB/api/contents/upload/SCB_SCB.png"},{"bankAbbr":"TCS","installments":[{"installId":239,"installmentAbb":"0%  3 เดือน ( 3 M)"},{"installId":239,"installmentAbb":"0%  3 เดือน ( 3 M)"},{"installId":241,"installmentAbb":"0%  6 เดือน ( 6 M)"},{"installId":241,"installmentAbb":"0%  6 เดือน ( 6 M)"},{"installId":246,"installmentAbb":"0% 10 เดือน (10 M)"},{"installId":246,"installmentAbb":"0% 10 เดือน (10 M)"}],"bankDescEn":"TESCO LOTUS VISA CARD","bankDescTh":"บัตรเครดิต เทสโก้ โลตัส วีซ่า","imageUrl":"https://cpc.ais.co.th/CPC-FE-WEB/api/contents/upload/TCS_TescoLotus-CreditCard.png"},{"bankAbbr":"TMB","installments":[{"installId":981,"installmentAbb":"0% 4 เดือน (4 M)"},{"installId":982,"installmentAbb":"0% 10 เดือน (10 M)"},{"installId":51814,"installmentAbb":"0%  6 เดือน ( 6 M)"},{"installId":51818,"installmentAbb":"0% 20 เดือน (20 M)"},{"installId":51819,"installmentAbb":"0% 24 เดือน (24 M)"}],"bankDescEn":"THAI MILITARY BANK PUBLIC COMPANY LIMITED","bankDescTh":"ทหารไทย จำกัด (มหาชน)","imageUrl":"https://cpc.ais.co.th/CPC-FE-WEB/api/contents/upload/TTB_11-TTB-Logo.png"},{"bankAbbr":"UOB","installments":[{"installId":265,"installmentAbb":"0%  3 เดือน ( 3 M)"},{"installId":267,"installmentAbb":"0%  6 เดือน ( 6 M)"},{"installId":272,"installmentAbb":"0% 10 เดือน (10 M)"},{"installId":277,"installmentAbb":"0% 15 เดือน (15 M)"},{"installId":282,"installmentAbb":"0% 24 เดือน (24 M)"},{"installId":581,"installmentAbb":"0% 12 เดือน (12 M)"},{"installId":863,"installmentAbb":"0% 18 เดือน (18 M)"},{"installId":51828,"installmentAbb":"0%  36 เดือน (36 M)"}],"bankDescEn":"UNITED OVERSEAS BANK(THAI)PUBLIC COMPANY LIMITED","bankDescTh":"ยูโอบี จำกัด (มหาชน)","imageUrl":"https://cpc.ais.co.th/CPC-FE-WEB/api/contents/upload/UOB_UOB-bank.png"}]},{"cardType":"OTHER","method":"CC","banks":[{"bankAbbr":"ACS","installments":[{"installId":20,"installmentAbb":"0%  3 เดือน ( 3 M)"},{"installId":22,"installmentAbb":"0%  6 เดือน ( 6 M)"},{"installId":27,"installmentAbb":"0% 10 เดือน (10 M)"}],"bankDescEn":"Ayudlhya Card Services","bankDescTh":"อยุธยาคาร์ด เซอร์วิสเซส","imageUrl":"https://cpc.ais.co.th/CPC-FE-WEB/api/contents/upload/ACS_BAY03.png"},{"bankAbbr":"AEON","installments":[{"installId":294,"installmentAbb":"0% 10 เดือน (10 M)"},{"installId":51837,"installmentAbb":"0% 18 เดือน (18 M)"},{"installId":51941,"installmentAbb":"0.59% 20 เดือน (20M)"},{"installId":51961,"installmentAbb":"0.59% 12 เดือน (12M)"},{"installId":52001,"installmentAbb":"0.69% 24 เดือน (24 M)"}],"bankDescEn":"AEON THANA SINSAP (THAILAND) PCL.","bankDescTh":"บริษัทอิออนธนสินทรัพย์ (ไทยแลนด์) จำกัด (มหาชน)","imageUrl":"https://cpc.ais.co.th/CPC-FE-WEB/api/contents/upload/AEON_AEON-logo.png"},{"bankAbbr":"BAY","installments":[{"installId":38,"installmentAbb":"0%  3 เดือน ( 3 M)"},{"installId":41,"installmentAbb":"0%  6 เดือน ( 6 M)"},{"installId":47,"installmentAbb":"0% 10 เดือน (10 M)"}],"bankDescEn":"BANK OF AYUDHAYA PUBLIC COMPANY LIMITED","bankDescTh":"กรุงศรีอยุธยา จำกัด (มหาชน)","imageUrl":"https://cpc.ais.co.th/CPC-FE-WEB/api/contents/upload/BAY_BAY.png"},{"bankAbbr":"BBL","installments":[{"installId":60,"installmentAbb":"0% 4 เดือน (4 M)"},{"installId":65,"installmentAbb":"0%  6 เดือน ( 6 M)"},{"installId":71,"installmentAbb":"0% 10 เดือน (10 M)"}],"bankDescEn":"BANGKOK BANK PUBLIC COMPANY LIMITED","bankDescTh":"กรุงเทพ จำกัด (มหาชน)","imageUrl":"https://cpc.ais.co.th/CPC-FE-WEB/api/contents/upload/BBL_BBL.png"},{"bankAbbr":"CITI","installments":[{"installId":309,"installmentAbb":"0% 4 เดือน (4 M)"},{"installId":314,"installmentAbb":"0%  6 เดือน ( 6 M)"},{"installId":320,"installmentAbb":"0% 10 เดือน (10 M)"}],"bankDescEn":"CITIBANK N.A.","bankDescTh":"ซิตี้แบงก์","imageUrl":"https://cpc.ais.co.th/CPC-FE-WEB/api/contents/upload/CITI_CITI.png"},{"bankAbbr":"CITIREADY","installments":[{"installId":432,"installmentAbb":"0% 4 เดือน (4 M)"},{"installId":436,"installmentAbb":"0%  6 เดือน ( 6 M)"},{"installId":440,"installmentAbb":"0% 10 เดือน (10 M)"},{"installId":445,"installmentAbb":"0% 24 เดือน (24 M)"},{"installId":524,"installmentAbb":"0% 18 เดือน (18 M)"},{"installId":884,"installmentAbb":"0% 12 เดือน (12 M)"},{"installId":51883,"installmentAbb":"0% 30 เดือน (30M)"},{"installId":51886,"installmentAbb":"0%  40 เดือน (40 M)"}],"bankDescEn":"CITIBANK Ready","bankDescTh":"ซิตี้แบงก์ เรดดี้เครดิต","imageUrl":"https://cpc.ais.co.th/CPC-FE-WEB/api/contents/upload/CITIREADY_citibank02.jpg"},{"bankAbbr":"CT","installments":[{"installId":2,"installmentAbb":"0%  3 เดือน ( 3 M)"},{"installId":2,"installmentAbb":"0%  3 เดือน ( 3 M)"},{"installId":4,"installmentAbb":"0%  6 เดือน ( 6 M)"},{"installId":4,"installmentAbb":"0%  6 เดือน ( 6 M)"},{"installId":10,"installmentAbb":"0% 10 เดือน (10 M)"},{"installId":10,"installmentAbb":"0% 10 เดือน (10 M)"}],"bankDescEn":"Central","bankDescTh":"เซ็นทรัล","imageUrl":"https://cpc.ais.co.th/CPC-FE-WEB/api/contents/upload/CT_ct_logo.png"},{"bankAbbr":"FCC","installments":[{"installId":108,"installmentAbb":"0%  6 เดือน ( 6 M)"},{"installId":112,"installmentAbb":"0% 10 เดือน (10 M)"},{"installId":136,"installmentAbb":"0.89% 20 เดือน (20 M)"},{"installId":461,"installmentAbb":"0% 15 เดือน (15 M)"},{"installId":722,"installmentAbb":"0% 20 เดือน (20 M)"},{"installId":846,"installmentAbb":"0% 12 เดือน (12 M)"}],"bankDescEn":"Frist Choice Credit Card","bankDescTh":"บัตรเครดิต เฟิร์สช้อยส์","imageUrl":"https://cpc.ais.co.th/CPC-FE-WEB/api/contents/upload/FCC_fcc_logo.png"},{"bankAbbr":"KBNK","installments":[{"installId":350,"installmentAbb":"0% 4 เดือน (4 M)"},{"installId":355,"installmentAbb":"0%  6 เดือน ( 6 M)"},{"installId":361,"installmentAbb":"0% 10 เดือน (10 M)"},{"installId":874,"installmentAbb":"0% 12 เดือน (12 M)"},{"installId":876,"installmentAbb":"0% 18 เดือน (18 M)"},{"installId":878,"installmentAbb":"0% 24 เดือน (24 M)"},{"installId":51860,"installmentAbb":"0%  36 เดือน (36 M)"}],"bankDescEn":"KASIKORNBANK PUBLIC COMPANY LIMITED","bankDescTh":"กสิกรไทย จำกัด (มหาชน)","imageUrl":"https://cpc.ais.co.th/CPC-FE-WEB/api/contents/upload/KBNK_kBank.png"},{"bankAbbr":"KTB","installments":[{"installId":161,"installmentAbb":"0%  6 เดือน ( 6 M)"},{"installId":167,"installmentAbb":"0% 10 เดือน (10 M)"},{"installId":462,"installmentAbb":"0% 12 เดือน (12 M)"},{"installId":849,"installmentAbb":"0% 18 เดือน (18 M)"},{"installId":51765,"installmentAbb":"0.59% 20 เดือน (20M)"}],"bankDescEn":"KRUNG THAI BANK PUBLIC COMPANY LIMITED","bankDescTh":"กรุงไทย จำกัด (มหาชน)","imageUrl":"https://cpc.ais.co.th/CPC-FE-WEB/api/contents/upload/KTB_KTB.png"},{"bankAbbr":"NBNK","installments":[{"installId":373,"installmentAbb":"0% 4 เดือน (4 M)"},{"installId":378,"installmentAbb":"0%  6 เดือน ( 6 M)"},{"installId":384,"installmentAbb":"0% 10 เดือน (10 M)"},{"installId":395,"installmentAbb":"0% 20 เดือน (20 M)"},{"installId":397,"installmentAbb":"0% 24 เดือน (24 M)"}],"bankDescEn":"THANACHART BANK PUBLIC COMPANY LIMITED","bankDescTh":"ธนชาต จำกัด(มหาชน)","imageUrl":"https://cpc.ais.co.th/CPC-FE-WEB/api/contents/upload/NBNK_65-NBNK-Logo.png"},{"bankAbbr":"SCB","installments":[{"installId":191,"installmentAbb":"0% 4 เดือน (4 M)"},{"installId":196,"installmentAbb":"0%  6 เดือน ( 6 M)"},{"installId":202,"installmentAbb":"0% 10 เดือน (10 M)"},{"installId":214,"installmentAbb":"0% 24 เดือน (24 M)"},{"installId":463,"installmentAbb":"0% 18 เดือน (18 M)"},{"installId":854,"installmentAbb":"0% 12 เดือน (12 M)"}],"bankDescEn":"SIAM COMMERCIAL BANK PUBLIC COMPANY LIMITED","bankDescTh":"ไทยพาณิชย์ จำกัด (มหาชน)","imageUrl":"https://cpc.ais.co.th/CPC-FE-WEB/api/contents/upload/SCB_SCB.png"},{"bankAbbr":"TCS","installments":[{"installId":239,"installmentAbb":"0%  3 เดือน ( 3 M)"},{"installId":239,"installmentAbb":"0%  3 เดือน ( 3 M)"},{"installId":241,"installmentAbb":"0%  6 เดือน ( 6 M)"},{"installId":241,"installmentAbb":"0%  6 เดือน ( 6 M)"},{"installId":246,"installmentAbb":"0% 10 เดือน (10 M)"},{"installId":246,"installmentAbb":"0% 10 เดือน (10 M)"}],"bankDescEn":"TESCO LOTUS VISA CARD","bankDescTh":"บัตรเครดิต เทสโก้ โลตัส วีซ่า","imageUrl":"https://cpc.ais.co.th/CPC-FE-WEB/api/contents/upload/TCS_TescoLotus-CreditCard.png"},{"bankAbbr":"TMB","installments":[{"installId":981,"installmentAbb":"0% 4 เดือน (4 M)"},{"installId":982,"installmentAbb":"0% 10 เดือน (10 M)"},{"installId":51814,"installmentAbb":"0%  6 เดือน ( 6 M)"},{"installId":51818,"installmentAbb":"0% 20 เดือน (20 M)"},{"installId":51819,"installmentAbb":"0% 24 เดือน (24 M)"}],"bankDescEn":"THAI MILITARY BANK PUBLIC COMPANY LIMITED","bankDescTh":"ทหารไทย จำกัด (มหาชน)","imageUrl":"https://cpc.ais.co.th/CPC-FE-WEB/api/contents/upload/TTB_11-TTB-Logo.png"},{"bankAbbr":"UOB","installments":[{"installId":265,"installmentAbb":"0%  3 เดือน ( 3 M)"},{"installId":267,"installmentAbb":"0%  6 เดือน ( 6 M)"},{"installId":272,"installmentAbb":"0% 10 เดือน (10 M)"},{"installId":277,"installmentAbb":"0% 15 เดือน (15 M)"},{"installId":282,"installmentAbb":"0% 24 เดือน (24 M)"},{"installId":581,"installmentAbb":"0% 12 เดือน (12 M)"},{"installId":863,"installmentAbb":"0% 18 เดือน (18 M)"},{"installId":51828,"installmentAbb":"0%  36 เดือน (36 M)"}],"bankDescEn":"UNITED OVERSEAS BANK(THAI)PUBLIC COMPANY LIMITED","bankDescTh":"ยูโอบี จำกัด (มหาชน)","imageUrl":"https://cpc.ais.co.th/CPC-FE-WEB/api/contents/upload/UOB_UOB-bank.png"}]},{"cardType":"VISA","method":"CC","banks":[{"bankAbbr":"ACS","installments":[{"installId":20,"installmentAbb":"0%  3 เดือน ( 3 M)"},{"installId":22,"installmentAbb":"0%  6 เดือน ( 6 M)"},{"installId":27,"installmentAbb":"0% 10 เดือน (10 M)"}],"bankDescEn":"Ayudlhya Card Services","bankDescTh":"อยุธยาคาร์ด เซอร์วิสเซส","imageUrl":"https://cpc.ais.co.th/CPC-FE-WEB/api/contents/upload/ACS_BAY03.png"},{"bankAbbr":"AEON","installments":[{"installId":294,"installmentAbb":"0% 10 เดือน (10 M)"},{"installId":51837,"installmentAbb":"0% 18 เดือน (18 M)"},{"installId":51941,"installmentAbb":"0.59% 20 เดือน (20M)"},{"installId":51961,"installmentAbb":"0.59% 12 เดือน (12M)"},{"installId":52001,"installmentAbb":"0.69% 24 เดือน (24 M)"}],"bankDescEn":"AEON THANA SINSAP (THAILAND) PCL.","bankDescTh":"บริษัทอิออนธนสินทรัพย์ (ไทยแลนด์) จำกัด (มหาชน)","imageUrl":"https://cpc.ais.co.th/CPC-FE-WEB/api/contents/upload/AEON_AEON-logo.png"},{"bankAbbr":"BAY","installments":[{"installId":38,"installmentAbb":"0%  3 เดือน ( 3 M)"},{"installId":41,"installmentAbb":"0%  6 เดือน ( 6 M)"},{"installId":47,"installmentAbb":"0% 10 เดือน (10 M)"}],"bankDescEn":"BANK OF AYUDHAYA PUBLIC COMPANY LIMITED","bankDescTh":"กรุงศรีอยุธยา จำกัด (มหาชน)","imageUrl":"https://cpc.ais.co.th/CPC-FE-WEB/api/contents/upload/BAY_BAY.png"},{"bankAbbr":"BBL","installments":[{"installId":60,"installmentAbb":"0% 4 เดือน (4 M)"},{"installId":65,"installmentAbb":"0%  6 เดือน ( 6 M)"},{"installId":71,"installmentAbb":"0% 10 เดือน (10 M)"}],"bankDescEn":"BANGKOK BANK PUBLIC COMPANY LIMITED","bankDescTh":"กรุงเทพ จำกัด (มหาชน)","imageUrl":"https://cpc.ais.co.th/CPC-FE-WEB/api/contents/upload/BBL_BBL.png"},{"bankAbbr":"CITI","installments":[{"installId":309,"installmentAbb":"0% 4 เดือน (4 M)"},{"installId":314,"installmentAbb":"0%  6 เดือน ( 6 M)"},{"installId":320,"installmentAbb":"0% 10 เดือน (10 M)"}],"bankDescEn":"CITIBANK N.A.","bankDescTh":"ซิตี้แบงก์","imageUrl":"https://cpc.ais.co.th/CPC-FE-WEB/api/contents/upload/CITI_CITI.png"},{"bankAbbr":"CITIREADY","installments":[{"installId":432,"installmentAbb":"0% 4 เดือน (4 M)"},{"installId":436,"installmentAbb":"0%  6 เดือน ( 6 M)"},{"installId":440,"installmentAbb":"0% 10 เดือน (10 M)"},{"installId":445,"installmentAbb":"0% 24 เดือน (24 M)"},{"installId":524,"installmentAbb":"0% 18 เดือน (18 M)"},{"installId":884,"installmentAbb":"0% 12 เดือน (12 M)"},{"installId":51883,"installmentAbb":"0% 30 เดือน (30M)"},{"installId":51886,"installmentAbb":"0%  40 เดือน (40 M)"}],"bankDescEn":"CITIBANK Ready","bankDescTh":"ซิตี้แบงก์ เรดดี้เครดิต","imageUrl":"https://cpc.ais.co.th/CPC-FE-WEB/api/contents/upload/CITIREADY_citibank02.jpg"},{"bankAbbr":"CT","installments":[{"installId":2,"installmentAbb":"0%  3 เดือน ( 3 M)"},{"installId":2,"installmentAbb":"0%  3 เดือน ( 3 M)"},{"installId":4,"installmentAbb":"0%  6 เดือน ( 6 M)"},{"installId":4,"installmentAbb":"0%  6 เดือน ( 6 M)"},{"installId":10,"installmentAbb":"0% 10 เดือน (10 M)"},{"installId":10,"installmentAbb":"0% 10 เดือน (10 M)"}],"bankDescEn":"Central","bankDescTh":"เซ็นทรัล","imageUrl":"https://cpc.ais.co.th/CPC-FE-WEB/api/contents/upload/CT_ct_logo.png"},{"bankAbbr":"FCC","installments":[{"installId":108,"installmentAbb":"0%  6 เดือน ( 6 M)"},{"installId":112,"installmentAbb":"0% 10 เดือน (10 M)"},{"installId":136,"installmentAbb":"0.89% 20 เดือน (20 M)"},{"installId":461,"installmentAbb":"0% 15 เดือน (15 M)"},{"installId":722,"installmentAbb":"0% 20 เดือน (20 M)"},{"installId":846,"installmentAbb":"0% 12 เดือน (12 M)"}],"bankDescEn":"Frist Choice Credit Card","bankDescTh":"บัตรเครดิต เฟิร์สช้อยส์","imageUrl":"https://cpc.ais.co.th/CPC-FE-WEB/api/contents/upload/FCC_fcc_logo.png"},{"bankAbbr":"KBNK","installments":[{"installId":350,"installmentAbb":"0% 4 เดือน (4 M)"},{"installId":355,"installmentAbb":"0%  6 เดือน ( 6 M)"},{"installId":361,"installmentAbb":"0% 10 เดือน (10 M)"},{"installId":874,"installmentAbb":"0% 12 เดือน (12 M)"},{"installId":876,"installmentAbb":"0% 18 เดือน (18 M)"},{"installId":878,"installmentAbb":"0% 24 เดือน (24 M)"},{"installId":51860,"installmentAbb":"0%  36 เดือน (36 M)"}],"bankDescEn":"KASIKORNBANK PUBLIC COMPANY LIMITED","bankDescTh":"กสิกรไทย จำกัด (มหาชน)","imageUrl":"https://cpc.ais.co.th/CPC-FE-WEB/api/contents/upload/KBNK_kBank.png"},{"bankAbbr":"KTB","installments":[{"installId":161,"installmentAbb":"0%  6 เดือน ( 6 M)"},{"installId":167,"installmentAbb":"0% 10 เดือน (10 M)"},{"installId":462,"installmentAbb":"0% 12 เดือน (12 M)"},{"installId":849,"installmentAbb":"0% 18 เดือน (18 M)"},{"installId":51765,"installmentAbb":"0.59% 20 เดือน (20M)"}],"bankDescEn":"KRUNG THAI BANK PUBLIC COMPANY LIMITED","bankDescTh":"กรุงไทย จำกัด (มหาชน)","imageUrl":"https://cpc.ais.co.th/CPC-FE-WEB/api/contents/upload/KTB_KTB.png"},{"bankAbbr":"NBNK","installments":[{"installId":373,"installmentAbb":"0% 4 เดือน (4 M)"},{"installId":378,"installmentAbb":"0%  6 เดือน ( 6 M)"},{"installId":384,"installmentAbb":"0% 10 เดือน (10 M)"},{"installId":395,"installmentAbb":"0% 20 เดือน (20 M)"},{"installId":397,"installmentAbb":"0% 24 เดือน (24 M)"}],"bankDescEn":"THANACHART BANK PUBLIC COMPANY LIMITED","bankDescTh":"ธนชาต จำกัด(มหาชน)","imageUrl":"https://cpc.ais.co.th/CPC-FE-WEB/api/contents/upload/NBNK_65-NBNK-Logo.png"},{"bankAbbr":"SCB","installments":[{"installId":191,"installmentAbb":"0% 4 เดือน (4 M)"},{"installId":196,"installmentAbb":"0%  6 เดือน ( 6 M)"},{"installId":202,"installmentAbb":"0% 10 เดือน (10 M)"},{"installId":214,"installmentAbb":"0% 24 เดือน (24 M)"},{"installId":463,"installmentAbb":"0% 18 เดือน (18 M)"},{"installId":854,"installmentAbb":"0% 12 เดือน (12 M)"}],"bankDescEn":"SIAM COMMERCIAL BANK PUBLIC COMPANY LIMITED","bankDescTh":"ไทยพาณิชย์ จำกัด (มหาชน)","imageUrl":"https://cpc.ais.co.th/CPC-FE-WEB/api/contents/upload/SCB_SCB.png"},{"bankAbbr":"TCS","installments":[{"installId":239,"installmentAbb":"0%  3 เดือน ( 3 M)"},{"installId":239,"installmentAbb":"0%  3 เดือน ( 3 M)"},{"installId":241,"installmentAbb":"0%  6 เดือน ( 6 M)"},{"installId":241,"installmentAbb":"0%  6 เดือน ( 6 M)"},{"installId":246,"installmentAbb":"0% 10 เดือน (10 M)"},{"installId":246,"installmentAbb":"0% 10 เดือน (10 M)"}],"bankDescEn":"TESCO LOTUS VISA CARD","bankDescTh":"บัตรเครดิต เทสโก้ โลตัส วีซ่า","imageUrl":"https://cpc.ais.co.th/CPC-FE-WEB/api/contents/upload/TCS_TescoLotus-CreditCard.png"},{"bankAbbr":"TMB","installments":[{"installId":981,"installmentAbb":"0% 4 เดือน (4 M)"},{"installId":982,"installmentAbb":"0% 10 เดือน (10 M)"},{"installId":51814,"installmentAbb":"0%  6 เดือน ( 6 M)"},{"installId":51818,"installmentAbb":"0% 20 เดือน (20 M)"},{"installId":51819,"installmentAbb":"0% 24 เดือน (24 M)"}],"bankDescEn":"THAI MILITARY BANK PUBLIC COMPANY LIMITED","bankDescTh":"ทหารไทย จำกัด (มหาชน)","imageUrl":"https://cpc.ais.co.th/CPC-FE-WEB/api/contents/upload/TTB_11-TTB-Logo.png"},{"bankAbbr":"UOB","installments":[{"installId":265,"installmentAbb":"0%  3 เดือน ( 3 M)"},{"installId":267,"installmentAbb":"0%  6 เดือน ( 6 M)"},{"installId":272,"installmentAbb":"0% 10 เดือน (10 M)"},{"installId":277,"installmentAbb":"0% 15 เดือน (15 M)"},{"installId":282,"installmentAbb":"0% 24 เดือน (24 M)"},{"installId":581,"installmentAbb":"0% 12 เดือน (12 M)"},{"installId":863,"installmentAbb":"0% 18 เดือน (18 M)"},{"installId":51828,"installmentAbb":"0%  36 เดือน (36 M)"}],"bankDescEn":"UNITED OVERSEAS BANK(THAI)PUBLIC COMPANY LIMITED","bankDescTh":"ยูโอบี จำกัด (มหาชน)","imageUrl":"https://cpc.ais.co.th/CPC-FE-WEB/api/contents/upload/UOB_UOB-bank.png"}]},{"method":"CA","banks":[]},{"method":"CC","banks":[]},{"method":"CI","banks":[]},{"method":"CP","banks":[]},{"method":"DC","banks":[]},{"method":"GV","banks":[]},{"method":"PB","banks":[]},{"method":"QP","banks":[]},{"method":"RL","banks":[]},{"method":"V1","banks":[]},{"method":"V2","banks":[]}],"freegoods":[],"privileges":[],"criterias":[],"channels":[{"saleChannel":"LOCALRETAILCHAIN","province":"ALL"},{"saleChannel":"RETAILCHAIN","province":"ALL"},{"saleChannel":"BRANDSHOP","province":"ALL"},{"saleChannel":"MODERNTRADE","province":"ALL"},{"saleChannel":"ARS","province":"ALL"},{"saleChannel":"ITCHAIN","province":"ALL"},{"saleChannel":"ITDISTRIBUTOR","province":"ALL"},{"saleChannel":"ITRETAIL","province":"ALL"},{"saleChannel":"TELEWIZ","province":"ALL"},{"saleChannel":"ASP","province":"ALL"},{"saleChannel":"AISBUDDYEXCLUSIVE","province":"ALL"},{"saleChannel":"AISBUDDY","province":"ALL"}],"tradeName":"AWN PRODUCT_FULL PAYMENT AND INSTALLMENT_APPLE_PARTNER","campaignName":"Handset Trading","saleType":"SALE","startDate":"2022-05-30T17:00:00Z","endDate":"2025-12-31T16:59:00Z"}],"company":"AWN","brand":"APPLE","model":"IPHONEXSM256","color":"GOLD","productType":"DEVICE","productSubtype":"HANDSET"}]}